LICENSE.rst
LICENSE_GPL.rst
MANIFEST.in
README.rst
setup.py
src/agx/__init__.py
src/agx.generator.pyegg.egg-info/PKG-INFO
src/agx.generator.pyegg.egg-info/SOURCES.txt
src/agx.generator.pyegg.egg-info/dependency_links.txt
src/agx.generator.pyegg.egg-info/entry_points.txt
src/agx.generator.pyegg.egg-info/namespace_packages.txt
src/agx.generator.pyegg.egg-info/not-zip-safe
src/agx.generator.pyegg.egg-info/requires.txt
src/agx.generator.pyegg.egg-info/top_level.txt
src/agx/generator/__init__.py
src/agx/generator/pyegg/__init__.py
src/agx/generator/pyegg/configure.zcml
src/agx/generator/pyegg/connectors.py
src/agx/generator/pyegg/generator.rst
src/agx/generator/pyegg/hierarchy.py
src/agx/generator/pyegg/integration.rst
src/agx/generator/pyegg/profiles.py
src/agx/generator/pyegg/scope.py
src/agx/generator/pyegg/semantics.py
src/agx/generator/pyegg/tests.py
src/agx/generator/pyegg/treesync.py
src/agx/generator/pyegg/utils.py
src/agx/generator/pyegg/profiles/README.txt
src/agx/generator/pyegg/profiles/pyegg.profile.di
src/agx/generator/pyegg/profiles/pyegg.profile.notation
src/agx/generator/pyegg/profiles/pyegg.profile.uml
src/agx/generator/pyegg/resources/model_templates/python_egg/manifest.txt
src/agx/generator/pyegg/resources/model_templates/python_egg/model.di
src/agx/generator/pyegg/resources/model_templates/python_egg/model.notation
src/agx/generator/pyegg/resources/model_templates/python_egg/model.uml
src/agx/generator/pyegg/resources/model_templates/python_egg/model.uml.agx
src/agx/generator/pyegg/resources/model_templates/python_egg/uml_profiles/pyegg.profile.uml
src/agx/generator/pyegg/templates/LICENSE.rst.jinja
src/agx/generator/pyegg/templates/MANIFEST.in.jinja
src/agx/generator/pyegg/templates/README.rst.jinja
src/agx/generator/pyegg/templates/setup.py.jinja
src/agx/generator/pyegg/testing/__init__.py
src/agx/generator/pyegg/testing/data/agx.testpackage.di
src/agx/generator/pyegg/testing/data/agx.testpackage.notation
src/agx/generator/pyegg/testing/data/agx.testpackage.uml
src/agx/generator/pyegg/testing/data/legacy/agx.testpackage.di2
src/agx/generator/pyegg/testing/data/legacy/agx.testpackage.uml